[
    {
        "image": "1.JPG",
        "title": "01",
        "tag": "",
        "colors": "black"
    },
    {
        "image": "2.JPG",
        "title": "02",
        "tag": "",    
        "colors": "white"
    },
    {
        "image": "3.JPG",
        "title": "03",
        "tag": "",
        "colors": "blue"
    },
    {
        "image": "4.JPG",
        "title": "04",
        "tag": "",
        "colors": "gold"
    },
    {
        "image": "5.JPG",
        "title": "05",
        "tag": "",
        "colors": "red"
    },
    {
        "image": "6.JPG",
        "title": "06",
        "tag": "",
        "colors": "silver"
    },
    {
        "image": "7.JPG",
        "title": "07",
        "tag": "",
        "colors": "green"
    },
    {
        "image": "8.JPG",
        "title": "08",
        "tag": "",
        "colors": "red"
    },
    {
        "image": "9.JPG",
        "title": "09",
        "tag": "",
        "colors": "gold"
    },
    {
        "image": "10.JPG",
        "title": "10",
        "tag": "people, arrows",
        "colors": "black"
    },
    {
        "image": "11.JPG",
        "title": "11",
        "tag": "people",
        "colors": "silver"
    },
    {
        "image": "12.JPG",
        "title": "12",
        "tag": "animals",
        "colors": "silver"
    },
    {
        "image": "13.JPG",
        "title": "13",
        "tag": "plants",
        "colors": "gold"
    },
    {
        "image": "14.JPG",
        "title": "14",
        "tag": "plants",
        "colors": "gold"
    },
    {
        "image": "15.JPG",
        "title": "15",
        "tag": "plants",
        "colors": "blue"
    },
    {
        "image": "16.JPG",
        "title": "16",
        "tag": "animals",
        "colors": "gold"
    },
    {
        "image": "17.JPG",
        "title": "17",
        "tag": "animals, wrecks",
        "colors": "green"
    },
    {
        "image": "18.JPG",
        "title": "18",
        "tag": "animals",
        "colors": "red"
    },
    {
        "image": "19.JPG",
        "title": "19",
        "tag": "animals",
        "colors": "orange"
    },
    {
        "image": "20.JPG",
        "title": "20",
        "tag": "animals",
        "colors": "black"
    },
    {
        "image": "21.JPG",
        "title": "21",
        "tag": "animals",
        "colors": "gold"
    },
    {
        "image": "22.JPG",
        "title": "22",
        "tag": "animals",
        "colors": "white"
    },
    {
        "image": "23.JPG",
        "title": "23",
        "tag": "animals",
        "colors": "black"
    },
    {
        "image": "24.JPG",
        "title": "24",
        "tag": "animals",
        "colors": "red"
    },
    {
        "image": "25.JPG",
        "title": "25",
        "tag": "animals",
        "colors": "red"
    },
    {
        "image": "26.JPG",
        "title": "26",
        "tag": "people",
        "colors": "yellow"
    },  
    {
        "image": "27.JPG",
        "title": "27",
        "tag": "objects",
        "colors": "black"
    },  
    {
        "image": "28.JPG",
        "title": "28",
        "tag": "objects, people",
        "colors": "silver"
    },
    {
        "image": "29.JPG",
        "title": "29",
        "tag": "",
        "colors": "green"
    },
    {
        "image": "30.JPG",
        "title": "30",
        "tag": "people, wrecks",
        "colors": "red"
    },
    {
        "image": "31.JPG",
        "title": "31",
        "tag": "objects, arrows",
        "colors": "red"
    },
    {
        "image": "32.JPG",
        "title": "1664",
        "tag": "animals, objects",
        "colors": "blue"
    },
    {
        "image": "33.JPG",
        "title": "250 ml",
        "tag": "",
        "colors": "red"
    },
    {
        "image": "34.JPG",
        "title": "Acqua Panna - Firenze",
        "tag": "plants",
        "colors": "red"
    },
    {
        "image": "35.JPG",
        "title": "Adler Bräu",
        "tag": "animals",
        "colors": "gold"
    },  
    {
        "image": "36.JPG",
        "title": "Adler Bräu - Schwande GL - seit 1828",
        "tag": "animals",
        "colors": "gold"
    },  
    {
        "image": "37.JPG",
        "title": "Adlerpliff",
        "tag": "animals",
        "colors": "yellow"
    },
    {
        "image": "38.JPG",
        "title": "Alkoholfrei - No alcohol",
        "tag": "",
        "colors": "red"
    },
    {
        "image": "39.JPG",
        "title": "Almdudler",
        "tag": "",
        "colors": "red"
    },
    {
        "image": "40.JPG",
        "title": "An excessive consumption of alcoholic drinks (...)",
        "tag": "",
        "colors": "gold"
    },
    {
        "image": "41.JPG",
        "title": "Angelo Poretti",
        "tag": "wrecks",
        "colors": "gold"
    },
    {
        "image": "42.JPG",
        "title": "Angelo Poretti Birrificio",
        "tag": "",
        "colors": "gold"
    },
    {
        "image": "43.JPG",
        "title": "Anheuser Busch",
        "tag": "wrecks",
        "colors": "red"
    },
    {
        "image": "44.JPG",
        "title": "Aperol Soda",
        "tag": "",
        "colors": "blue"
    },
    {
        "image": "45.JPG",
        "title": "Appenzeller Bier",
        "tag": "animals, objects, plants",
        "colors": "white"
    },
    {
        "image": "46.JPG",
        "title": "Appenzeller Bier",
        "tag": "animals, objects, plants, arrows",
        "colors": "white"
    },
    {
        "image": "47.JPG",
        "title": "Archina",
        "tag": "",
        "colors": "green"
    },
    {
        "image": "48.JPG",
        "title": "Archina",
        "tag": "",
        "colors": "blue"
    },
    {
        "image": "49.JPG",
        "title": "Archina Yverdon",
        "tag": "",
        "colors": "green"
    },
    {
        "image": "50.JPG",
        "title": "Archina Yverdon",
        "tag": "",
        "colors": "blue"
    },
    {
        "image": "51.JPG",
        "title": "Asahi",
        "tag": "",
        "colors": "black"
    },
    {
        "image": "52.JPG",
        "title": "Bavaria Classica",
        "tag": "plants",
        "colors": "green"
    },
    {
        "image": "53.JPG",
        "title": "Bayerisches Bier",
        "tag": "animals, objects",
        "colors": "white"
    },
    {
        "image": "54.JPG",
        "title": "Beck's",
        "tag": "objects",
        "colors": "silver"
    },
    {
        "image": "55.JPG",
        "title": "Beck's Next",
        "tag": "objects, wrecks",
        "colors": "gold"
    },
    {
        "image": "56.JPG",
        "title": "Berg König",
        "tag": "wrecks",
        "colors": "gold"
    },
    {
        "image": "57.JPG",
        "title": "Berg König",
        "tag": "arrows",
        "colors": "gold"
    },
    {
        "image": "58.JPG",
        "title": "Bilz",
        "tag": "typography, arrows",
        "colors": "blue"
    },
    {
        "image": "59.JPG",
        "title": "Birra Moretti - Baffo d'Oro",
        "tag": "plants",
        "colors": "gold"
    },
    {
        "image": "60.JPG",
        "title": "Birra Moretti",
        "tag": "plants",
        "colors": "red"
    },
    {
        "image": "61.JPG",
        "title": "Birra Moretti - Zero",
        "tag": "plants",
        "colors": "white"
    },
    {
        "image": "62.JPG",
        "title": "Birra Moretti",
        "tag": "people",
        "colors": "gold"
    },
    {
        "image": "63.JPG",
        "title": "Birra Peroni",
        "tag": "",
        "colors": "red"
    },
    {
        "image": "64.JPG",
        "title": "Birra Peroni",
        "tag": "plants, animals",
        "colors": "white"
    },
    {
        "image": "65.JPG",
        "title": "Boon Rawd Brewery Co.",
        "tag": "animals",
        "colors": "red"
    },
    {
        "image": "66.JPG",
        "title": "Brasserie D'Achouffe",
        "tag": "people",
        "colors": "orange"
    },
    {
        "image": "67.JPG",
        "title": "Brasserie D'Achouffe",
        "tag": "people",
        "colors": "yellow"
    },
    {
        "image": "68.JPG",
        "title": "Bud",
        "tag": "objects",
        "colors": "red"
    },
    {
        "image": "69.JPG",
        "title": "Calanda",
        "tag": "animals",
        "colors": "white"
    },
    {
        "image": "70.JPG",
        "title": "Calanda - Edelbräu",
        "tag": "animals",
        "colors": "white"
    },
    {
        "image": "71.JPG",
        "title": "Calanda - Senza",
        "tag": "animals",
        "colors": "white"
    },
    {
        "image": "72.JPG",
        "title": "Calanda - Blonde",
        "tag": "arrows",
        "colors": "yellow"
    },
    {
        "image": "73.JPG",
        "title": "Cardinal - Draft",
        "tag": "",
        "colors": "gold"
    },
    {
        "image": "74.JPG",
        "title": "Cardinal - Lager",
        "tag": "arrows",
        "colors": "yellow"
    },
    {
        "image": "75.JPG",
        "title": "Camparisoda",
        "tag": "",
        "colors": "red"
    },
    {
        "image": "76.JPG",
        "title": "Camparisoda",
        "tag": "",
        "colors": "red"
    },
    {
        "image": "77.JPG",
        "title": "Carlsberg",
        "tag": "",
        "colors": "black"
    },
    {
        "image": "78.JPG",
        "title": "Carlsberg",
        "tag": "objects",
        "colors": "green"
    },
    {
        "image": "79.JPG",
        "title": "Carlsberg - Game",
        "tag": "objects",
        "colors": "green"
    },
    {
        "image": "80.JPG",
        "title": "Castello",
        "tag": "",
        "colors": "silver"
    },
    {
        "image": "81.JPG",
        "title": "Ceres",
        "tag": "objects",
        "colors": "white"
    },
    {
        "image": "82.JPG",
        "title": "Ceres - Denmark",
        "tag": "objects",
        "colors": "white"
    },
    {
        "image": "83.JPG",
        "title": "Chimay - Trappist",
        "tag": "",
        "colors": "white"
    },
    {
        "image": "84.JPG",
        "title": "Chimay - Trappist",
        "tag": "",
        "colors": "blue"
    },
    {
        "image": "85.JPG",
        "title": "Chimay - Trappist",
        "tag": "",
        "colors": "white"
    },
    {
        "image": "86.JPG",
        "title": "Clausthaler - Classic",
        "tag": "",
        "colors": "white"
    },
    {
        "image": "87.JPG",
        "title": "Clausthaler",
        "tag": "objects",
        "colors": "white"
    },
    {
        "image": "88.JPG",
        "title": "Coca-Cola",
        "tag": "",
        "colors": "red"
    },
    {
        "image": "89.JPG",
        "title": "Coca-Cola",
        "tag": "",
        "colors": "red"
    },
    {
        "image": "90.JPG",
        "title": "Coca-Cola - Light",
        "tag": "",
        "colors": "silver"
    },
    {
        "image": "91.JPG",
        "title": "Coca-Cola - Light",
        "tag": "",
        "colors": "silver"
    },
    {
        "image": "92.JPG",
        "title": "Coca-Cola - Zero",
        "tag": "",
        "colors": "black"
    },
    {
        "image": "93.JPG",
        "title": "Coca-Cola - Zero",
        "tag": "",
        "colors": "black"
    },
    {
        "image": "94.JPG",
        "title": "Codoni - Mendrisio",
        "tag": "stars",
        "colors": "black"
    },
    {
        "image": "95.JPG",
        "title": "Como Italy - Acque Minerali",
        "tag": "",
        "colors": "blue"
    },
    {
        "image": "96.JPG",
        "title": "Corona Extra",
        "tag": "objects",
        "colors": "blue"
    },
    {
        "image": "97.JPG",
        "title": "Crodino",
        "tag": "",
        "colors": "red"
    },
    {
        "image": "98.JPG",
        "title": "Crodino",
        "tag": "",
        "colors": "red"
    },
    {
        "image": "99.JPG",
        "title": "Crodino",
        "tag": "",
        "colors": "white"
    },
    {
        "image": "100.JPG",
        "title": "Cubanero",
        "tag": "",
        "colors": "black"
    },
    {
        "image": "101.JPG",
        "title": "Dab",
        "tag": "",
        "colors": "green"
    },
    {
        "image": "102.JPG",
        "title": "Daura",
        "tag": "",
        "colors": "red"
    },
    {
        "image": "103.JPG",
        "title": "Desperados",
        "tag": "",
        "colors": "gold"
    },
    {
        "image": "104.JPG",
        "title": "Desperados",
        "tag": "",
        "colors": "gold"
    },
    {
        "image": "105.JPG",
        "title": "Duff Beer",
        "tag": "",
        "colors": "red"
    },
    {
        "image": "106.JPG",
        "title": "Duuel",
        "tag": "objects",
        "colors": "white"
    },
    {
        "image": "107.JPG",
        "title": "Edelspez - Premium",
        "tag": "people",
        "colors": "gold"
    },
    {
        "image": "108.JPG",
        "title": "Efes",
        "tag": "",
        "colors": "blue"
    },
    {
        "image": "109.JPG",
        "title": "Efes",
        "tag": "arrows",
        "colors": "blue"
    },
    {
        "image": "110.JPG",
        "title": "Eichhof - Alkoholfrei",
        "tag": "animals, objects, plants",
        "colors": "white"
    },
    {
        "image": "111.JPG",
        "title": "Eichhof - Barbara",
        "tag": "animals, objects, plants",
        "colors": "black"
    },
    {
        "image": "112.JPG",
        "title": "Eichhof - Braungold",
        "tag": "animals, objects, plants",
        "colors": "white"
    },
    {
        "image": "113.JPG",
        "title": "Eichhof - Lager",
        "tag": "animals, objects, plants, arrows",
        "colors": "yellow"
    },
    {
        "image": "114.JPG",
        "title": "Eichhof - Lager",
        "tag": "animals, objects, plants",
        "colors": "yellow"
    },
    {
        "image": "115.JPG",
        "title": "Eichhof - Spiess",
        "tag": "animals, objects, plants",
        "colors": "white"
    },
    {
        "image": "116.JPG",
        "title": "Elmer - Mineral",
        "tag": "",
        "colors": "blue"
    },
    {
        "image": "117.JPG",
        "title": "Erdinger - Weissbrau",
        "tag": "plants",
        "colors": "red"
    },
    {
        "image": "118.JPG",
        "title": "Erdinger - Weissbrau - Alkoholfrei",
        "tag": "plants",
        "colors": "blue"
    },
    {
        "image": "119.JPG",
        "title": "Eve",
        "tag": "plants",
        "colors": "white"
    },
    {
        "image": "120.JPG",
        "title": "Eve - Litchi",
        "tag": "",
        "colors": "white"
    },
    {
        "image": "121.JPG",
        "title": "Fanta",
        "tag": "plants, typography",
        "colors": "silver"
    },
    {
        "image": "122.JPG",
        "title": "Feldschlösschen",
        "tag": "places, arrows",
        "colors": "gold"
    },
    {
        "image": "123.JPG",
        "title": "Feldschlösschen",
        "tag": "places",
        "colors": "gold"
    },
    {
        "image": "124.JPG",
        "title": "Feldschlösschen",
        "tag": "places, wrecks, arrows",
        "colors": "white"
    },
    {
        "image": "125.JPG",
        "title": "Feldschlösschen - Alkoholfrei",
        "tag": "places",
        "colors": "gold"
    },
    {
        "image": "126.JPG",
        "title": "Feldschlösschen - Alkoholfrei",
        "tag": "places",
        "colors": "gold"
    },
    {
        "image": "127.JPG",
        "title": "Feldschlösschen - Dunkle Perle",
        "tag": "places",
        "colors": "gold"
    },
    {
        "image": "128.JPG",
        "title": "Feldschlösschen - Hopfenperle",
        "tag": "places",
        "colors": "gold"
    },
    {
        "image": "129.JPG",
        "title": "Feldschlösschen - Original",
        "tag": "places",
        "colors": "gold"
    },
    {
        "image": "130.JPG",
        "title": "Feldschlösschen - Premium",
        "tag": "places, wrecks",
        "colors": "gold"
    },
    {
        "image": "131.JPG",
        "title": "Feldschlösschen - Selection",
        "tag": "places",
        "colors": "gold"
    },
    {
        "image": "132.JPG",
        "title": "First",
        "tag": "",
        "colors": "red"
    },
    {
        "image": "133.JPG",
        "title": "F O",
        "tag": "typography",
        "colors": "gold"
    },
    {
        "image": "134.JPG",
        "title": "Golden Fire",
        "tag": "wrecks",
        "colors": "green"
    },
    {
        "image": "135.JPG",
        "title": "Guinnes",
        "tag": "objects",
        "colors": "white"
    },
    {
        "image": "136.JPG",
        "title": "Halden Krone",
        "tag": "",
        "colors": "white"
    },
    {
        "image": "137.JPG",
        "title": "HB",
        "tag": "objects",
        "colors": "blue"
    },
    {
        "image": "138.JPG",
        "title": "HB",
        "tag": "arrows",
        "colors": "yellow"
    },
    {
        "image": "139.JPG",
        "title": "Heineken - Beer",
        "tag": "stars",
        "colors": "green"
    },
    {
        "image": "140.JPG",
        "title": "Heineken - Quality",
        "tag": "stars",
        "colors": "green"
    },
    {
        "image": "141.JPG",
        "title": "Henniez - Légère",
        "tag": "stars",
        "colors": "green"
    },
    {
        "image": "142.JPG",
        "title": "Henniez - Légère",
        "tag": "",
        "colors": "green"
    },
    {
        "image": "143.JPG",
        "title": "Henniez - Gazéifiée",
        "tag": "stars",
        "colors": "red"
    },
    {
        "image": "144.JPG",
        "title": "Henniez - Gazéifiée",
        "tag": "",
        "colors": "red"
    },
    {
        "image": "145.JPG",
        "title": "Henniez - Naturelle",
        "tag": "stars",
        "colors": "blue"
    },
    {
        "image": "146.JPG",
        "title": "Henniez - Naturelle",
        "tag": "",
        "colors": "blue"
    },
    {
        "image": "147.JPG",
        "title": "Hoegaarden",
        "tag": "",
        "colors": "silver"
    },
    {
        "image": "148.JPG",
        "title": "Jacobsen",
        "tag": "people",
        "colors": "black"
    },
    {
        "image": "149.JPG",
        "title": "Kilkenny",
        "tag": "places",
        "colors": "silver"
    },
    {
        "image": "150.JPG",
        "title": "Kronenbourg",
        "tag": "arrows",
        "colors": "white"
    },
    {
        "image": "151.JPG",
        "title": "Kuchlbauer - Weissbierbrauer",
        "tag": "people",
        "colors": "white"
    },
    {
        "image": "152.JPG",
        "title": "Leermond - Vollmond",
        "tag": "stars",
        "colors": "blue"
    },
    {
        "image": "153.JPG",
        "title": "Lemon Soda",
        "tag": "plants, typography",
        "colors": "black"
    },
    {
        "image": "154.JPG",
        "title": "Lindemans",
        "tag": "objects",
        "colors": "gold"
    },
    {
        "image": "155.JPG",
        "title": "London Pride",
        "tag": "",
        "colors": "red"
    },
    {
        "image": "156.JPG",
        "title": "Löwenbräu - Alkoholfrei",
        "tag": "animals",
        "colors": "blue"
    },
    {
        "image": "157.JPG",
        "title": "Made in Switzerland",
        "tag": "places",
        "colors": "black"
    },
    {
        "image": "158.JPG",
        "title": "Made in Switzerland",
        "tag": "places",
        "colors": "red"
    },
    {
        "image": "159.JPG",
        "title": "Meckatzer",
        "tag": "objects, wrecks",
        "colors": "white"
    },
    {
        "image": "160.JPG",
        "title": "Menabrea",
        "tag": "",
        "colors": "white"
    },
    {
        "image": "161.JPG",
        "title": "MGD",
        "tag": "",
        "colors": "black"
    },
    {
        "image": "162.JPG",
        "title": "Miller",
        "tag": "arrows",
        "colors": "black"
    },
    {
        "image": "163.JPG",
        "title": "Mineralquelle",
        "tag": "animals, places",
        "colors": "silver"
    },
    {
        "image": "164.JPG",
        "title": "Mineralquelle",
        "tag": "animals, places",
        "colors": "silver"
    },
    {
        "image": "165.JPG",
        "title": "Monsteiner Bier",
        "tag": "places",
        "colors": "white"
    },
    {
        "image": "166.JPG",
        "title": "Naturaplan",
        "tag": "places, plants, wrecks, arrows",
        "colors": "white"
    },
    {
        "image": "167.JPG",
        "title": "Nestea",
        "tag": "plants",
        "colors": "yellow"
    },
    {
        "image": "168.JPG",
        "title": "Nestea",
        "tag": "plants",
        "colors": "orange"
    },
    {
        "image": "169.JPG",
        "title": "Obi",
        "tag": "typography",
        "colors": "green"
    },
    {
        "image": "170.JPG",
        "title": "P - Open",
        "tag": "plants, wrecks, arrows",
        "colors": "white"
    },
    {
        "image": "171.JPG",
        "title": "Paulaner München",
        "tag": "people",
        "colors": "gold"
    },
    {
        "image": "172.JPG",
        "title": "Peroncino",
        "tag": "",
        "colors": "red"
    },
    {
        "image": "173.JPG",
        "title": "Phoenix",
        "tag": "animals",
        "colors": "gold"
    },
    {
        "image": "174.JPG",
        "title": "Ramseier",
        "tag": "",
        "colors": "red"
    },
    {
        "image": "175.JPG",
        "title": "Red Stripe",
        "tag": "",
        "colors": "white"
    },
    {
        "image": "176.JPG",
        "title": "Reissdorf Kölsch",
        "tag": "plants",
        "colors": "red"
    },
    {
        "image": "177.JPG",
        "title": "Rivella",
        "tag": "",
        "colors": "white"
    },
    {
        "image": "178.JPG",
        "title": "Rivella",
        "tag": "",
        "colors": "white"
    },
    {
        "image": "179.JPG",
        "title": "Rivella",
        "tag": "",
        "colors": "white"
    },
    {
        "image": "180.JPG",
        "title": "Rugnebräu - birra - biere - beer",
        "tag": "animals, plants",
        "colors": "white"
    },
    {
        "image": "181.JPG",
        "title": "Sagres Cerveja",
        "tag": "",
        "colors": "red"
    },
    {
        "image": "182.JPG",
        "title": "Sagres Cerveja",
        "tag": "",
        "colors": "gold"
    },
    {
        "image": "183.JPG",
        "title": "Salitos Ice",
        "tag": "",
        "colors": "blue"
    },
    {
        "image": "184.JPG",
        "title": "Sanbittèr",
        "tag": "stars",
        "colors": "red"
    },
    {
        "image": "185.JPG",
        "title": "Sanbittèr",
        "tag": "stars",
        "colors": "silver"
    },
    {
        "image": "186.JPG",
        "title": "Sanbittèr",
        "tag": "stars",
        "colors": "blue"
    },
    {
        "image": "187.JPG",
        "title": "Sanbittèr",
        "tag": "stars",
        "colors": "red"
    },
    {
        "image": "188.JPG",
        "title": "Sanbittèr",
        "tag": "stars",
        "colors": "red"
    },
    {
        "image": "189.JPG",
        "title": "Sanbittèr",
        "tag": "stars",
        "colors": "silver"
    },
    {
        "image": "190.JPG",
        "title": "San Martino",
        "tag": "",
        "colors": "red"
    },
    {
        "image": "191.JPG",
        "title": "San Martino",
        "tag": "",
        "colors": "yellow"
    },
    {
        "image": "192.JPG",
        "title": "San Miguel",
        "tag": "objects",
        "colors": "gold"
    },
    {
        "image": "193.JPG",
        "title": "Sanpellegrino",
        "tag": "stars",
        "colors": "green"
    },
    {
        "image": "194.JPG",
        "title": "Sanpellegrino",
        "tag": "stars",
        "colors": "blue"
    },
    {
        "image": "195.JPG",
        "title": "Sanpellegrino",
        "tag": "stars",
        "colors": "black"
    },
    {
        "image": "196.JPG",
        "title": "Sanpellegrino",
        "tag": "stars",
        "colors": "black"
    },
    {
        "image": "197.JPG",
        "title": "Sanpellegrino",
        "tag": "stars",
        "colors": "black"
    },
    {
        "image": "198.JPG",
        "title": "Sanpellegrino",
        "tag": "stars",
        "colors": "blue"
    },
    {
        "image": "199.JPG",
        "title": "Sanpellegrino",
        "tag": "stars",
        "colors": "orange"
    },
    {
        "image": "200.JPG",
        "title": "Sanpellegrino",
        "tag": "stars",
        "colors": "orange"
    },
    {
        "image": "201.JPG",
        "title": "Santal",
        "tag": "wrecks",
        "colors": "white"
    },
    {
        "image": "202.JPG",
        "title": "Schneider Weisse - Original",
        "tag": "",
        "colors": "blue"
    },
    {
        "image": "203.JPG",
        "title": "Schlossbrauerei",
        "tag": "places",
        "colors": "white"
    },
    {
        "image": "204.JPG",
        "title": "Schöfferhofer - Hefeweizen",
        "tag": "objects",
        "colors": "orange"
    },
    {
        "image": "205.JPG",
        "title": "Schörle",
        "tag": "plants",
        "colors": "black"
    },
    {
        "image": "206.JPG",
        "title": "Schwarzer Bär - seit 1779",
        "tag": "animals",
        "colors": "brown"
    },
    {
        "image": "207.JPG",
        "title": "Schweppes",
        "tag": "",
        "colors": "yellow"
    },
    {
        "image": "208.JPG",
        "title": "Schweppes",
        "tag": "",
        "colors": "gold"
    },
    {
        "image": "209.JPG",
        "title": "Sinalco",
        "tag": "typography",
        "colors": "red"
    },
    {
        "image": "210.JPG",
        "title": "Smirnoff",
        "tag": "animals",
        "colors": "red"
    },
    {
        "image": "211.JPG",
        "title": "Sonnenbräu - Rebstein",
        "tag": "animals, places",
        "colors": "white"
    },
    {
        "image": "212.JPG",
        "title": "Sonnenbräu - Rebstein",
        "tag": "animals, places",
        "colors": "gold"
    },
    {
        "image": "213.JPG",
        "title": "Spezial - Brauerei",
        "tag": "",
        "colors": "white"
    },
    {
        "image": "214.JPG",
        "title": "Sprite",
        "tag": "typography",
        "colors": "blue"
    },
    {
        "image": "215.JPG",
        "title": "Spritz",
        "tag": "",
        "colors": "orange"
    },
    {
        "image": "216.JPG",
        "title": "Stella Artois",
        "tag": "plants, objects",
        "colors": "white"
    },
    {
        "image": "217.JPG",
        "title": "Sumol laranja",
        "tag": "",
        "colors": "red"
    },
    {
        "image": "218.JPG",
        "title": "Sumol laranja",
        "tag": "",
        "colors": "green"
    },
    {
        "image": "219.JPG",
        "title": "Super Bock",
        "tag": "",
        "colors": "red"
    },
    {
        "image": "220.JPG",
        "title": "Super Bock",
        "tag": "",
        "colors": "black"
    },
    {
        "image": "221.JPG",
        "title": "Svitare - Drehen - Dévisser",
        "tag": "arrows",
        "colors": "white"
    },
    {
        "image": "222.JPG",
        "title": "Svitare - Drehen - Dévisser",
        "tag": "arrows",
        "colors": "gold"
    },
    {
        "image": "223.JPG",
        "title": "Svitare - Drehen - Dévisser",
        "tag": "arrows",
        "colors": "gold"
    },
    {
        "image": "224.JPG",
        "title": "Svitare - Drehen - Dévisser",
        "tag": "animals, arrows",
        "colors": "white"
    },
    {
        "image": "225.JPG",
        "title": "T",
        "tag": "typography",
        "colors": "gold"
    },
    {
        "image": "226.JPG",
        "title": "Tegernseer Bier",
        "tag": "objects",
        "colors": "silver"
    },
    {
        "image": "227.JPG",
        "title": "Terme di Bognaco",
        "tag": "animals",
        "colors": "white"
    },
    {
        "image": "228.JPG",
        "title": "Tourner pou ouvrir - Twist off",
        "tag": "arrows",
        "colors": "silver"
    },
    {
        "image": "229.JPG",
        "title": "Tourner pou ouvrir - Twist off",
        "tag": "arrows",
        "colors": "gold"
    },
    {
        "image": "230.JPG",
        "title": "Trojka",
        "tag": "stars",
        "colors": "silver"
    },
    {
        "image": "231.JPG",
        "title": "Unser Bier",
        "tag": "people",
        "colors": "yellow"
    },
    {
        "image": "232.JPG",
        "title": "Valentino Weissier",
        "tag": "people, wrecks",
        "colors": "blue"
    },
    {
        "image": "233.JPG",
        "title": "Valser",
        "tag": "",
        "colors": "red"
    },
    {
        "image": "234.JPG",
        "title": "Valser Classic",
        "tag": "",
        "colors": "silver"
    },
    {
        "image": "235.JPG",
        "title": "Valser Classic",
        "tag": "",
        "colors": "silver"
    },
    {
        "image": "236.JPG",
        "title": "Valser Naturelle",
        "tag": "",
        "colors": "blue"
    },
    {
        "image": "237.JPG",
        "title": "Valser Naturelle",
        "tag": "",
        "colors": "white"
    },
    {
        "image": "238.JPG",
        "title": "Warfteiner",
        "tag": "objects, wrecks",
        "colors": "white"
    },
    {
        "image": "239.JPG",
        "title": "Weltenburger",
        "tag": "wrecks",
        "colors": "blue"
    },
    {
        "image": "240.JPG",
        "title": "Yoga - Optimum",
        "tag": "",
        "colors": "green"
    },
    {
        "image": "241.JPG",
        "title": "Züri-Hell",
        "tag": "",
        "colors": "black"
    },
    {
        "image": "242.JPG",
        "title": "Feldschlösschen",
        "tag": "places, arrows",
        "colors": "gold"
    },
    {
        "image": "243.JPG",
        "title": "Bayereuther Brauhaus",
        "tag": "objects",
        "colors": "white"
    },
    {
        "image": "244.JPG",
        "title": "Ice - Lime & Mint",
        "tag": "objects",
        "colors": "silver"
    },
    {
        "image": "245.JPG",
        "title": "Peroni - Nastro Azzurro",
        "tag": "",
        "colors": "white"
    },
    {
        "image": "246.JPG",
        "title": "München Bier",
        "tag": "people",
        "colors": "silver"
    },
    {
        "image": "247.JPG",
        "title": "Natur Radler - Zitrone",
        "tag": "people, objects",
        "colors": "yellow"
    },
    {
        "image": "248.JPG",
        "title": "Birra Messina",
        "tag": "plants",
        "colors": "blue"
    },
    {
        "image": "249.JPG",
        "title": "Angelo Poretti Birrificio",
        "tag": "",
        "colors": "blue"
    },
    {
        "image": "250.JPG",
        "title": "Grimbergen",
        "tag": "animals",
        "colors": "orange"
    },
    {
        "image": "251.JPG",
        "title": "Matta",
        "tag": "typography",
        "colors": "yellow"
    },
    {
        "image": "252.JPG",
        "title": "Heineken - 0.0",
        "tag": "stars",
        "colors": "blue"
    } 
]